iimi/__init__.py
iimi/globals.py
iimi/map.py
iimi/plot.py
iimi/predict_iimi.py
iimi/process.py
iimi/train_iimi.py
iimi/data/__init__.py
iimi/data/example_cov.pkl
iimi/data/example_diag.pkl
iimi/data/nucleotide_info.pkl
iimi/data/trained_en.pkl
iimi/data/trained_rf.pkl
iimi/data/trained_xgb.model
iimi/data/unreliable_regions.pkl
iimi/data/virus_segments.pkl
iimi-0.2.7.dist-info/LICENSE.md
iimi-0.2.7.dist-info/METADATA
iimi-0.2.7.dist-info/WHEEL
iimi-0.2.7.dist-info/top_level.txt
iimi-0.2.7.dist-info/RECORD
