Metadata-Version: 2.1
Name: iimi
Version: 0.2.7
Summary: identifying plant infection with machine intelligence.
Home-page: https://github.com/jaspreetks/iimi
Author: Jaspreet S
License: MIT
Keywords: bioinformatics,plant-virus,machine-learning,diagnostics
Platform: UNKNOWN
Classifier: Programming Language :: Python :: 3
Classifier: License :: OSI Approved :: MIT License
Classifier: Operating System :: OS Independent
Requires-Python: >=3.7
Requires-Dist: numpy
Requires-Dist: pandas
Requires-Dist: matplotlib
Requires-Dist: scikit-learn
Requires-Dist: joblib
Requires-Dist: xgboost
Requires-Dist: pysam
